pygensvd/_gsvd.cpython-38-darwin.so
pygensvd/__init__.py
pygensvd/.dylibs/libgfortran.5.dylib
pygensvd/.dylibs/libopenblasp-r0.3.23.dylib
pygensvd/.dylibs/libquadmath.0.dylib
pygensvd/.dylibs/libgcc_s.1.1.dylib
pygensvd/.dylibs/libgomp.1.dylib
pygensvd-0.1.0.dist-info/RECORD
pygensvd-0.1.0.dist-info/WHEEL
pygensvd-0.1.0.dist-info/top_level.txt
pygensvd-0.1.0.dist-info/LICENSE.txt
pygensvd-0.1.0.dist-info/METADATA
