Metadata-Version: 2.1
Name: pygensvd
Version: 0.1.0
Summary: Python and NumPy extension module implementing the generalized signular value decomposition (GSVD).
Author-email: Andrew Van <vanandrew@wustl.edu>
License: GNU License
Project-URL: github, https://github.com/vanandrew/pygensvd
Keywords: GSVD
Classifier: Programming Language :: Python :: 3
Requires-Python: >=3.7
Provides-Extra: dev
License-File: LICENSE.txt
